[
  {
    "id": "1ejf7JQSM2-kvclr1oZW6jH_a0K_aEZuGQCYOD7RcO8U",
    "name": "PLH activity library",
    "mimeType": "application/vnd.google-apps.spreadsheet",
    "modifiedTime": "2025-09-23T11:41:29.997Z",
    "folderPath": "",
    "lastModifyingUser": {
      "displayName": "Esmee te Winkel"
    },
    "relativePath": "PLH activity library.xlsx"
  },
  {
    "id": "1m32rmsgJOAetXH4yFvYTW8l20poja-lYfkFSWrrgIHY",
    "name": "PLH app_launch",
    "mimeType": "application/vnd.google-apps.spreadsheet",
    "modifiedTime": "2025-07-15T15:55:43.744Z",
    "folderPath": "",
    "lastModifyingUser": {
      "displayName": "Esmee te Winkel"
    },
    "relativePath": "PLH app_launch.xlsx"
  },
  {
    "id": "1jWVWtpRFixLG5K_m2vQIKnhqTMAIq6_F0pSdApBQ1jc",
    "name": "PLH app_navigation",
    "mimeType": "application/vnd.google-apps.spreadsheet",
    "modifiedTime": "2025-09-19T11:56:09.891Z",
    "folderPath": "",
    "lastModifyingUser": {
      "displayName": "Christopher Marsh"
    },
    "relativePath": "PLH app_navigation.xlsx"
  },
  {
    "id": "1Zq6UzQ4qUIsCt_tg1TKDndZjOHmidmW5h1dyTpnoPTE",
    "name": "PLH articles template generators",
    "mimeType": "application/vnd.google-apps.spreadsheet",
    "modifiedTime": "2025-05-29T09:00:07.433Z",
    "folderPath": "",
    "lastModifyingUser": {
      "displayName": "Esmee te Winkel"
    },
    "relativePath": "PLH articles template generators.xlsx"
  },
  {
    "id": "13WrrsCwjK_5S9t8VQTbgWbWpAVbRKByxpOXr95YnjY8",
    "name": "PLH module_navigation",
    "mimeType": "application/vnd.google-apps.spreadsheet",
    "modifiedTime": "2025-12-19T12:09:13.162Z",
    "folderPath": "",
    "lastModifyingUser": {
      "displayName": "Christopher Marsh"
    },
    "relativePath": "PLH module_navigation.xlsx"
  },
  {
    "id": "19AalUbQp0r3QwEz82OPw-aq80SFtROYZBkhQ3Xp8rNs",
    "name": "PLH modules_data_pipes",
    "mimeType": "application/vnd.google-apps.spreadsheet",
    "modifiedTime": "2025-09-16T15:41:09.970Z",
    "folderPath": "",
    "lastModifyingUser": {
      "displayName": "Christopher Marsh"
    },
    "relativePath": "PLH modules_data_pipes.xlsx"
  },
  {
    "id": "1uBEmZtqR_EeWZCjDQ6i6fdL56Vh8IasbzpEGTVlmNvs",
    "name": "PLH settings",
    "mimeType": "application/vnd.google-apps.spreadsheet",
    "modifiedTime": "2025-11-07T16:50:54.436Z",
    "folderPath": "",
    "lastModifyingUser": {
      "displayName": "Esmee te Winkel"
    },
    "relativePath": "PLH settings.xlsx"
  }
]